ipfs_datasets/__init__.py
ipfs_datasets/ipfs_datasets.py
ipfs_datasets/ipfs_knn_index.py
ipfs_datasets/s3_kit.py
ipfs_datasets/test_fio.py
ipfs_datasets-0.0.4.dist-info/LICENSE
ipfs_datasets-0.0.4.dist-info/METADATA
ipfs_datasets-0.0.4.dist-info/WHEEL
ipfs_datasets-0.0.4.dist-info/top_level.txt
ipfs_datasets-0.0.4.dist-info/RECORD
